<?xml version="1.0" encoding="UTF-8"?>
<databaseChangeLog xmlns="http://www.liquibase.org/xml/ns/dbchangelog"
                   xmlns:xsi="http://www.w3.org/2001/XMLSchema-instance"
                   xsi:schemaLocation="http://www.liquibase.org/xml/ns/dbchangelog
                   https://www.liquibase.org/xml/ns/dbchangelog/dbchangelog-latest.xsd">

    <changeSet id="2025-08-12.1" author="Lars Aaberg">
        <createTable tableName="tenant">
            <column name="id" type="int8" autoIncrement="true">
                <constraints nullable="false" primaryKey="true" primaryKeyName="pk_tenant" />
            </column>
            <column name="name" type="varchar(255)">
                <constraints nullable="false" />
            </column>
            <column name="type" type="varchar(50)">
                <constraints nullable="false" />
            </column>
            <column name="created" type="timestamp with time zone" defaultValueComputed="current_timestamp">
                <constraints nullable="false" />
            </column>
        </createTable>
    </changeSet>
    <changeSet id="2025-08-12.Tenant.2" author="Lars Aaberg">
        <createTable tableName="tenant_member">
            <column name="user_id" type="varchar(50)">
                <constraints nullable="false" />
            </column>
            <column name="tenant_id" type="int8">
                <constraints
                        referencedTableName="tenant"
                        referencedColumnNames="id"
                        foreignKeyName="fk_tenant"
                        nullable="false"
                />
            </column>
            <column name="role" type="varchar(20)">
                <constraints nullable="false" />
            </column>
        </createTable>
    </changeSet>

    <changeSet id="2025-11-09-1" author="Lars Aaberg">
        <createTable tableName="contact2">
            <column name="id" type="uuid"><constraints nullable="false" primaryKey="true" primaryKeyName="pk_contact2"/></column>
            <column name="tenant_id" type="int8">
                <constraints referencedTableName="tenant" referencedColumnNames="id"
                             foreignKeyName="fk_contact_with_details_tenant"/>
            </column>
            <column name="last_updated" type="timestamp"><constraints nullable="false"/></column>
            <column name="data" type="jsonb"><constraints nullable="false"/></column>
        </createTable>
    </changeSet>
</databaseChangeLog>